{
	"database": "/opt/xchem-fragalysis-2/maxwin/BulkDock/TARGETS/D68EV3C/D68EV3C.sqlite",
	"timestamp": "2025-03-14 12:22:40.717595",
	"price": {
		"amount": 10499.0,
		"currency": "EUR"
	},
	"reactant_supplier": [
		"Stock",
		"Enamine"
	],
	"reactants": {
		"compound_id": [
			18027,
			18083,
			51607,
			51611,
			21385,
			21471,
			13126,
			28670,
			13159,
			29789,
			14284,
			46569,
			35318,
			35417,
			14291,
			43823,
			41039,
			45808,
			7274,
			7339,
			14991,
			15074,
			53805,
			31795,
			31881,
			41858,
			38944,
			39005,
			16650,
			16700,
			34614,
			51995,
			7316,
			7348,
			51638,
			31866,
			41890,
			14295,
			41065,
			14297,
			34621,
			7428,
			43841,
			51792,
			38957,
			7328,
			7351,
			31855,
			43905,
			29831,
			41859,
			28681,
			52121,
			52124,
			34630,
			13243,
			41042,
			7433,
			7402,
			15061,
			29801
		],
		"amount": [
			1.0,
			2.0,
			6.0,
			1.0,
			2.0,
			1.0,
			7.0,
			1.0,
			1.0,
			1.0,
			1.0,
			1.0,
			1.0,
			1.0,
			10.0,
			1.0,
			3.0,
			3.0,
			8.0,
			3.0,
			1.0,
			3.0,
			3.0,
			1.0,
			6.0,
			1.0,
			1.0,
			2.0,
			1.0,
			1.0,
			1.0,
			1.0,
			4.0,
			3.0,
			1.0,
			1.0,
			1.0,
			5.0,
			3.0,
			5.0,
			3.0,
			1.0,
			1.0,
			1.0,
			1.0,
			4.0,
			3.0,
			1.0,
			1.0,
			1.0,
			1.0,
			1.0,
			1.0,
			1.0,
			1.0,
			1.0,
			3.0,
			1.0,
			1.0,
			1.0,
			1.0
		],
		"quote_id": [
			9121,
			8953,
			9226,
			9394,
			10274,
			11299,
			9626,
			11277,
			9264,
			9594,
			10185,
			9975,
			9240,
			10123,
			7035,
			9924,
			9850,
			9427,
			9567,
			9946,
			7504,
			9551,
			6314,
			7133,
			5747,
			9760,
			7357,
			10782,
			10761,
			9479,
			11230,
			10034,
			10629,
			10849,
			10251,
			6538,
			10652,
			9999,
			10594,
			8519,
			6748,
			11119,
			10115,
			11329,
			9356,
			9177,
			10947,
			6608,
			10027,
			11347,
			5789,
			10724,
			10453,
			8498,
			9878,
			9618,
			10332,
			11146,
			10506,
			9647,
			10857
		],
		"supplier": [
			"Enamine",
			"Enamine",
			"Enamine",
			"Enamine",
			"Enamine",
			"Enamine",
			"Enamine",
			"Enamine",
			"Enamine",
			"Enamine",
			"Enamine",
			"Enamine",
			"Enamine",
			"Enamine",
			"Enamine",
			"Enamine",
			"Enamine",
			"Enamine",
			"Enamine",
			"Enamine",
			"Enamine",
			"Enamine",
			"Enamine",
			"Enamine",
			"Enamine",
			"Enamine",
			"Enamine",
			"Enamine",
			"Enamine",
			"Enamine",
			"Enamine",
			[
				"Stock",
				"Enamine"
			],
			[
				"Stock",
				"Enamine"
			],
			[
				"Stock",
				"Enamine"
			],
			[
				"Stock",
				"Enamine"
			],
			[
				"Stock",
				"Enamine"
			],
			[
				"Stock",
				"Enamine"
			],
			[
				"Stock",
				"Enamine"
			],
			[
				"Stock",
				"Enamine"
			],
			[
				"Stock",
				"Enamine"
			],
			[
				"Stock",
				"Enamine"
			],
			[
				"Stock",
				"Enamine"
			],
			[
				"Stock",
				"Enamine"
			],
			[
				"Stock",
				"Enamine"
			],
			[
				"Stock",
				"Enamine"
			],
			[
				"Stock",
				"Enamine"
			],
			[
				"Stock",
				"Enamine"
			],
			[
				"Stock",
				"Enamine"
			],
			[
				"Stock",
				"Enamine"
			],
			[
				"Stock",
				"Enamine"
			],
			[
				"Stock",
				"Enamine"
			],
			[
				"Stock",
				"Enamine"
			],
			[
				"Stock",
				"Enamine"
			],
			[
				"Stock",
				"Enamine"
			],
			[
				"Stock",
				"Enamine"
			],
			[
				"Stock",
				"Enamine"
			],
			[
				"Stock",
				"Enamine"
			],
			[
				"Stock",
				"Enamine"
			],
			[
				"Stock",
				"Enamine"
			],
			[
				"Stock",
				"Enamine"
			],
			[
				"Stock",
				"Enamine"
			]
		],
		"max_lead_time": [
			null,
			null,
			null,
			null,
			null,
			null,
			null,
			null,
			null,
			null,
			null,
			null,
			null,
			null,
			null,
			null,
			null,
			null,
			null,
			null,
			null,
			null,
			null,
			null,
			null,
			null,
			null,
			null,
			null,
			null,
			null,
			null,
			null,
			null,
			null,
			null,
			null,
			null,
			null,
			null,
			null,
			null,
			null,
			null,
			null,
			null,
			null,
			null,
			null,
			null,
			null,
			null,
			null,
			null,
			null,
			null,
			null,
			null,
			null,
			null,
			null
		],
		"quoted_amount": [
			100.0,
			100.0,
			50.0,
			50.0,
			50.0,
			50.0,
			50.0,
			50.0,
			50.0,
			50.0,
			50.0,
			50.0,
			50.0,
			50.0,
			100.0,
			50.0,
			50.0,
			50.0,
			50.0,
			50.0,
			100.0,
			50.0,
			100.0,
			100.0,
			100.0,
			50.0,
			100.0,
			50.0,
			50.0,
			50.0,
			50.0,
			50.0,
			50.0,
			50.0,
			50.0,
			100.0,
			50.0,
			50.0,
			50.0,
			100.0,
			100.0,
			50.0,
			50.0,
			50.0,
			50.0,
			100.0,
			50.0,
			100.0,
			50.0,
			50.0,
			100.0,
			50.0,
			50.0,
			100.0,
			50.0,
			50.0,
			50.0,
			50.0,
			50.0,
			50.0,
			50.0
		]
	},
	"intermediates": {
		"compound_id": [],
		"amount": [],
		"quote_id": [],
		"supplier": [],
		"max_lead_time": [],
		"quoted_amount": []
	},
	"products": {
		"compound_id": [
			2022,
			2134,
			2845,
			3233,
			3254,
			3264,
			3360,
			3996,
			5315,
			5316,
			5327,
			5856,
			5868,
			5906,
			7035,
			7036,
			7068,
			7190,
			7248,
			52813,
			8659,
			52171,
			32265,
			42022,
			41286,
			41391,
			34889,
			7889,
			44479,
			52406,
			39232,
			8818,
			32105,
			44543,
			30388,
			41941,
			28825,
			53252,
			53271,
			34898,
			14237,
			41255,
			8662,
			7894,
			7854,
			16186,
			21569,
			35184,
			41233,
			54773,
			46139,
			7449,
			7446,
			41225,
			46078,
			41158,
			8673,
			41305,
			8828,
			55068,
			8821,
			35227,
			15201,
			41135,
			30334
		],
		"amount": [
			1,
			1,
			1,
			1,
			1,
			1,
			1,
			1,
			1,
			1,
			1,
			1,
			1,
			1,
			1,
			1,
			1,
			1,
			1,
			1,
			1,
			1,
			1,
			1,
			1,
			1,
			1,
			1,
			1,
			1,
			1,
			1,
			1,
			1,
			1,
			1,
			1,
			1,
			1,
			1,
			1,
			1,
			1,
			1,
			1,
			1,
			1,
			1,
			1,
			1,
			1,
			1,
			1,
			1,
			1,
			1,
			1,
			1,
			1,
			1,
			1,
			1,
			1,
			1,
			1
		],
		"quote_id": [
			null,
			null,
			null,
			null,
			null,
			null,
			null,
			null,
			null,
			null,
			null,
			null,
			null,
			null,
			null,
			null,
			null,
			null,
			null,
			null,
			null,
			null,
			null,
			null,
			null,
			null,
			null,
			null,
			null,
			null,
			null,
			null,
			null,
			null,
			null,
			null,
			null,
			null,
			null,
			null,
			null,
			null,
			null,
			null,
			null,
			null,
			null,
			null,
			null,
			null,
			null,
			null,
			null,
			null,
			null,
			null,
			null,
			null,
			null,
			null,
			null,
			null,
			null,
			null,
			null
		],
		"supplier": [
			null,
			null,
			null,
			null,
			null,
			null,
			null,
			null,
			null,
			null,
			null,
			null,
			null,
			null,
			null,
			null,
			null,
			null,
			null,
			null,
			null,
			null,
			null,
			null,
			null,
			null,
			null,
			null,
			null,
			null,
			null,
			null,
			null,
			null,
			null,
			null,
			null,
			null,
			null,
			null,
			null,
			null,
			null,
			null,
			null,
			null,
			null,
			null,
			null,
			null,
			null,
			null,
			null,
			null,
			null,
			null,
			null,
			null,
			null,
			null,
			null,
			null,
			null,
			null,
			null
		],
		"max_lead_time": [
			null,
			null,
			null,
			null,
			null,
			null,
			null,
			null,
			null,
			null,
			null,
			null,
			null,
			null,
			null,
			null,
			null,
			null,
			null,
			null,
			null,
			null,
			null,
			null,
			null,
			null,
			null,
			null,
			null,
			null,
			null,
			null,
			null,
			null,
			null,
			null,
			null,
			null,
			null,
			null,
			null,
			null,
			null,
			null,
			null,
			null,
			null,
			null,
			null,
			null,
			null,
			null,
			null,
			null,
			null,
			null,
			null,
			null,
			null,
			null,
			null,
			null,
			null,
			null,
			null
		],
		"quoted_amount": [
			null,
			null,
			null,
			null,
			null,
			null,
			null,
			null,
			null,
			null,
			null,
			null,
			null,
			null,
			null,
			null,
			null,
			null,
			null,
			null,
			null,
			null,
			null,
			null,
			null,
			null,
			null,
			null,
			null,
			null,
			null,
			null,
			null,
			null,
			null,
			null,
			null,
			null,
			null,
			null,
			null,
			null,
			null,
			null,
			null,
			null,
			null,
			null,
			null,
			null,
			null,
			null,
			null,
			null,
			null,
			null,
			null,
			null,
			null,
			null,
			null,
			null,
			null,
			null,
			null
		]
	},
	"reaction_ids": [
		11264,
		1,
		22913,
		33152,
		20481,
		10,
		13,
		37391,
		28688,
		7570,
		32662,
		28696,
		29342,
		23199,
		26656,
		20641,
		37410,
		418,
		26788,
		23333,
		11297,
		4519,
		31143,
		36265,
		17453,
		28718,
		18351,
		28595,
		28854,
		28598,
		31161,
		36545,
		7106,
		453,
		1223,
		23242,
		6090,
		29259,
		1226,
		28749,
		20302,
		18895,
		29261,
		458,
		37842,
		38735,
		32723,
		28621,
		36310,
		1237,
		36952,
		28768,
		32483,
		1382,
		1385,
		6121,
		1392,
		22897,
		8820,
		17396,
		39030,
		22904,
		31225,
		5498,
		18841
	],
	"rgen_data_path": "/opt/xchem-fragalysis-2/maxwin/3C_FFF/hippo/D68EV3C_rgen.json",
	"rgen_db_path": "/opt/xchem-fragalysis-2/maxwin/BulkDock/TARGETS/D68EV3C/D68EV3C.sqlite",
	"rgen_recipe_dir": "/opt/xchem-fragalysis-2/maxwin/3C_FFF/hippo/D68EV3C_recipes",
	"rgen_max_lead_time": null,
	"rgen_suppliers": [
		"Stock",
		"Enamine"
	],
	"gen_budget": 10000,
	"gen_currency": "EUR",
	"gen_max_products": 3000,
	"gen_max_reactions": 6000,
	"gen_max_iter": 275,
	"gen_shuffle": true,
	"gen_iterations": 273,
	"gen_stop_reason": "Product pool depleted",
	"gen_recipe_path": "/opt/xchem-fragalysis-2/maxwin/3C_FFF/hippo/D68EV3C_recipes/Recipe_0FV4H2Q.json"
}